blobhand/__init__.py
blobhand/blob/__init__.py
blobhand/blob/reader.py
blobhand/blob/writer.py
azure_blob_handlers-0.1.0.dev1.dist-info/LICENSE
azure_blob_handlers-0.1.0.dev1.dist-info/METADATA
azure_blob_handlers-0.1.0.dev1.dist-info/WHEEL
azure_blob_handlers-0.1.0.dev1.dist-info/RECORD
